CHANGES.md
LICENSE
MANIFEST.in
README.md
setup.py
celery_graceful_stop/__init__.py
celery_graceful_stop/bootsteps.py
celery_graceful_stop/utils.py
celery_graceful_stop.egg-info/PKG-INFO
celery_graceful_stop.egg-info/SOURCES.txt
celery_graceful_stop.egg-info/dependency_links.txt
celery_graceful_stop.egg-info/requires.txt
celery_graceful_stop.egg-info/top_level.txt
systemd/celery@.service