Metadata-Version: 1.1
Name: celery-graceful-stop
Version: 0.0.1
Summary: Celery plugin thats adds ability to graceful stop worker
Home-page: https://github.com/MnogoByte/celery-graceful-stop
Author: Mikhail Antonov
Author-email: atin65536@gmail.com
License: BSD
Keywords: celery,stop,graceful,reload
Platform: UNKNOWN
Classifier: Intended Audience :: Developers
Classifier: Intended Audience :: System Administrators
Classifier: Operating System :: OS Independent
Classifier: Topic :: Software Development
Classifier: Programming Language :: Python :: 2.7
Classifier: Programming Language :: Python :: 3.4
Classifier: Programming Language :: Python :: 3.5
Classifier: Development Status :: 3 - Alpha
Classifier: License :: OSI Approved :: BSD License
